{"assets":[{"id":"4","layers":[{"ind":3,"ty":4,"ks":{},"ip":0,"op":97,"st":0,"shapes":[{"ty":"rc","p":{"a":0,"k":[128,128]},"r":{"a":0,"k":0},"s":{"a":0,"k":[256,256]}},{"ty":"fl","c":{"a":0,"k":[0,0,0,0]},"o":{"a":0,"k":0}}]},{"ind":0,"ty":4,"ks":{"s":{"a":0,"k":[133.33,133.33]}},"ip":0,"op":97,"st":0,"shapes":[{"ty":"gr","it":[{"ty":"gr","it":[{"ty":"sh","ks":{"a":0,"k":{"c":true,"i":[[0,0],[1.5,-3.52],[1.79,-0.78],[1.52,-3.51],[5.29,2.3],[-1.82,2.84],[-5.36,0.52]],"o":[[3.03,-0.29],[-0.8,1.88],[-3.5,1.52],[-1.32,3.04],[-4.25,-1.84],[2.89,-4.51],[0,0]],"v":[[35.07,65.87],[39.46,70.54],[32.67,73.33],[23.2,82.54],[16.93,92.27],[18.93,76.93],[35.07,65.87]]}}},{"ty":"fl","c":{"a":0,"k":[0.99,1,1,1]},"o":{"a":0,"k":100}},{"ty":"tr","o":{"a":0,"k":100}}]},{"ty":"gr","it":[{"ty":"sh","ks":{"a":0,"k":{"c":true,"i":[[0,0],[-0.61,-9.55],[20.7,-24.08],[24.05,-1.79],[0,0],[0,0],[-14.28,14.84],[16.18,10.57],[8.13,0.38],[2.19,5.47],[0.04,0.41],[-0.76,1.19]],"o":[[6.68,6.94],[30.94,4.11],[-17.84,20.75],[0,0],[0,0],[18.39,-1.6],[13.4,-13.93],[-6.95,-4.54],[1.5,-5.77],[-0.59,-1.48],[-0.08,-0.83],[0,0]],"v":[[142.8,25.07],[153.6,51.33],[178.93,116.93],[108.67,130.93],[108.4,130.4],[116.4,122.4],[171.46,112.93],[166,64.54],[143.73,58.8],[142.13,40.93],[137.87,33.73],[142.8,25.07]]}}},{"ty":"fl","c":{"a":0,"k":[0.99,1,1,1]},"o":{"a":0,"k":100}},{"ty":"tr","o":{"a":0,"k":100}}]},{"ty":"gr","it":[{"ty":"sh","ks":{"a":0,"k":{"c":true,"i":[[0,0],[0,0],[0,0],[0,0],[0,0],[0,0],[0,0],[0,0]],"o":[[0,0],[0,0],[0,0],[0,0],[0,0],[0,0],[0,0],[0,0]],"v":[[101.46,17.07],[136.27,17.46],[98.67,86.54],[135.73,87.33],[53.46,178.93],[91.2,105.73],[53.07,105.46],[101.46,17.07]]}}},{"ty":"fl","c":{"a":0,"k":[0.82,0.63,0.21,1]},"o":{"a":0,"k":100}},{"ty":"tr","o":{"a":0,"k":100}}]},{"ty":"gr","it":[{"ty":"sh","ks":{"a":0,"k":{"c":true,"i":[[0,0],[-5.6,-2.06],[0,0],[-4.86,-23.6],[7.23,-6.06],[-9.36,-13.33],[-19.87,-1.61],[-0.02,-0.37],[0.63,-0.92],[15.44,11.86],[-34.74,4.7],[-19.59,1.27]],"o":[[5.99,-0.39],[0,0],[-22.19,-7.79],[-9.22,0.38],[-12.5,10.46],[13.47,19.18],[0.25,0.22],[0.03,0.45],[-18.16,-0.86],[-28.42,-21.83],[0.18,-19.88],[0,0]],"v":[[73.46,13.07],[91.6,15.73],[87.07,24],[45.87,58.8],[20.93,66.67],[15.46,109.46],[73.73,122.4],[74.13,123.07],[69.73,130.93],[16.93,122.67],[36.27,51.33],[73.46,13.07]]}}},{"ty":"fl","c":{"a":0,"k":[0.99,1,1,1]},"o":{"a":0,"k":100}},{"ty":"tr","o":{"a":0,"k":100}}]},{"ty":"tr","o":{"a":0,"k":100}}]}]}]},{"id":"7","layers":[{"ind":6,"ty":0,"ks":{},"w":256,"h":256,"ip":0,"op":97,"st":0,"refId":"4"}]},{"id":"10","layers":[{"ind":9,"ty":0,"ks":{"a":{"a":0,"k":[128,128]},"o":{"a":1,"k":[{"t":0,"s":[0],"i":{"x":0.73,"y":0.459},"o":{"x":0.391,"y":0}},{"t":12.264,"s":[100],"i":{"x":0.635,"y":0.999},"o":{"x":0.301,"y":0.602}},{"t":19.5264,"s":[64.9],"i":{"x":0.725,"y":0.451},"o":{"x":0.388,"y":0.001}},{"t":26.7888,"s":[100],"i":{"x":0.611,"y":0.999},"o":{"x":0.273,"y":0.546}},{"t":31.0944,"s":[87.7],"i":{"x":0.559,"y":0.119},"o":{"x":0.206,"y":0.001}},{"t":35.3952,"s":[100],"i":{"x":0.607,"y":0.997},"o":{"x":0.27,"y":0.539}},{"t":37.944,"s":[95.7],"i":{"x":0.838,"y":0.676},"o":{"x":0.468,"y":0.002}},{"t":40.5024,"s":[100],"i":{"x":0.654,"y":0.996},"o":{"x":0.329,"y":0.654}},{"t":42.0144,"s":[98.5],"i":{"x":0.533,"y":0.068},"o":{"x":0.171,"y":0.001}},{"t":43.5312,"s":[100],"i":{"x":0.929,"y":0.999},"o":{"x":0.522,"y":1}},{"t":44.4336,"s":[99.5],"i":{"x":0.921,"y":0.842},"o":{"x":0.516,"y":0.009}},{"t":45.336,"s":[100],"i":{"x":1,"y":1},"o":{"x":0,"y":0}},{"t":45.8688,"s":[99.8],"i":{"x":1,"y":1},"o":{"x":0,"y":0}},{"t":46.4112,"s":[100],"h":1},{"t":96,"s":[100],"h":1}]},"p":{"a":0,"k":[128,128]},"s":{"a":1,"k":[{"t":0,"s":[50,50],"i":{"x":[0.73,0.73],"y":[0.459,0.459]},"o":{"x":[0.391,0.391],"y":[0,0]}},{"t":12.264,"s":[100,100],"i":{"x":[0.635,0.635],"y":[0.999,0.999]},"o":{"x":[0.301,0.301],"y":[0.602,0.602]}},{"t":19.524,"s":[82.46,82.46],"i":{"x":[0.725,0.725],"y":[0.451,0.451]},"o":{"x":[0.388,0.388],"y":[0.001,0.001]}},{"t":26.79,"s":[99.99,99.99],"i":{"x":[0.611,0.611],"y":[0.999,0.999]},"o":{"x":[0.273,0.273],"y":[0.546,0.546]}},{"t":31.092,"s":[93.84,93.84],"i":{"x":[0.559,0.559],"y":[0.119,0.119]},"o":{"x":[0.206,0.206],"y":[0.001,0.001]}},{"t":35.394,"s":[100,100],"i":{"x":[0.607,0.607],"y":[0.997,0.997]},"o":{"x":[0.27,0.27],"y":[0.539,0.539]}},{"t":37.944,"s":[97.83,97.83],"i":{"x":[0.838,0.838],"y":[0.676,0.676]},"o":{"x":[0.468,0.468],"y":[0.002,0.002]}},{"t":40.5,"s":[100,100],"i":{"x":[0.654,0.654],"y":[0.996,0.996]},"o":{"x":[0.329,0.329],"y":[0.654,0.654]}},{"t":42.012,"s":[99.24,99.24],"i":{"x":[0.533,0.533],"y":[0.068,0.068]},"o":{"x":[0.171,0.171],"y":[0.001,0.001]}},{"t":43.53,"s":[100,100],"i":{"x":[0.929,0.929],"y":[0.999,0.999]},"o":{"x":[0.522,0.522],"y":[1,1]}},{"t":44.436,"s":[99.73,99.73],"i":{"x":[0.921,0.921],"y":[0.842,0.842]},"o":{"x":[0.516,0.516],"y":[0.009,0.009]}},{"t":45.336,"s":[100,100],"i":{"x":[1,1],"y":[1,1]},"o":{"x":[0,0],"y":[0,0]}},{"t":45.87,"s":[99.9,99.9],"i":{"x":[1,1],"y":[1,1]},"o":{"x":[0,0],"y":[0,0]}},{"t":46.41,"s":[100,100],"i":{"x":[1,1],"y":[1,1]},"o":{"x":[0,0],"y":[0,0]}},{"t":96,"s":[100,100],"h":1}]}},"w":256,"h":256,"ip":0,"op":97,"st":0,"refId":"7"}]}],"fr":60,"h":300,"ip":0,"layers":[{"ind":12,"ty":0,"parent":2,"ks":{"a":{"a":0,"k":[128,128]},"o":{"a":1,"k":[{"t":0,"s":[100],"h":1},{"t":60,"s":[100],"i":{"x":0.65,"y":1},"o":{"x":0.35,"y":0}},{"t":67.2,"s":[120],"i":{"x":0.25,"y":1},"o":{"x":0.45,"y":0}},{"t":81.6,"s":[-10],"i":{"x":0.4,"y":1},"o":{"x":0.25,"y":0}},{"t":96,"s":[0],"h":1}]},"p":{"a":0,"k":[128,128]},"s":{"a":1,"k":[{"t":0,"s":[100,100],"i":{"x":[1,1],"y":[1,1]},"o":{"x":[0,0],"y":[0,0]}},{"t":60,"s":[100,100],"i":{"x":[0.65,0.65],"y":[1,1]},"o":{"x":[0.35,0.35],"y":[0,0]}},{"t":67.2,"s":[115,115],"i":{"x":[0.25,0.25],"y":[1,1]},"o":{"x":[0.45,0.45],"y":[0,0]}},{"t":81.6,"s":[17.5,17.5],"i":{"x":[0.4,0.4],"y":[1,1]},"o":{"x":[0.25,0.25],"y":[0,0]}},{"t":96,"s":[25,25],"h":1}]}},"w":256,"h":256,"ip":0,"op":97,"st":0,"refId":"10"},{"ind":2,"ty":3,"parent":1,"ks":{"p":{"a":0,"k":[22,22]}},"ip":0,"op":97,"st":0},{"ind":1,"ty":3,"parent":0,"ks":{},"ip":0,"op":97,"st":0},{"ind":0,"ty":3,"ks":{},"ip":0,"op":97,"st":0}],"meta":{"g":"https://jitter.video"},"op":96,"v":"5.7.4","w":300}